wavtoolkit/__init__.py
wavtoolkit/core.py
wavtoolkit-1.0.4.dist-info/METADATA
wavtoolkit-1.0.4.dist-info/WHEEL
wavtoolkit-1.0.4.dist-info/RECORD
