Metadata-Version: 2.3
Name: wavtoolkit
Version: 1.0.4
Summary: File operations and other tools for working with .WAV files
License: MIT
Author: DJ Stomp
Author-email: 85457381+DJStompZone@users.noreply.github.com
Requires-Python: >=3.10,<4.0
Classifier: License :: OSI Approved :: MIT License
Classifier: Programming Language :: Python :: 3
Classifier: Programming Language :: Python :: 3.10
Classifier: Programming Language :: Python :: 3.11
Classifier: Programming Language :: Python :: 3.12
Classifier: Programming Language :: Python :: 3.13
Requires-Dist: numpy (>=2.2.6,<3.0.0)
Requires-Dist: pyloudnorm (>=0.1.1,<0.2.0)
Requires-Dist: soundfile (>=0.13.1,<0.14.0)
Requires-Dist: wave-chunk-parser (>=1.5.0,<2.0.0)
